easy_ocr/__init__.py
easy_ocr/baidu.py
easy_ocr/base.py
easy_ocr/xueersi.py
easy_ocr/youdao.py
easy_ocr-0.1.1.dist-info/METADATA
easy_ocr-0.1.1.dist-info/WHEEL
easy_ocr-0.1.1.dist-info/top_level.txt
easy_ocr-0.1.1.dist-info/RECORD
